vehicle_detector/__init__.py
vehicle_detector/vehicle_detection.py
vehicle_detection_package-0.3.dist-info/METADATA
vehicle_detection_package-0.3.dist-info/WHEEL
vehicle_detection_package-0.3.dist-info/top_level.txt
vehicle_detection_package-0.3.dist-info/RECORD
