Metadata-Version: 2.1
Name: vehicle-detection-package
Version: 0.3
Summary: A package for vehicle detection and tracking using YOLOv8 and SORT
Home-page: UNKNOWN
Author: muiz
Author-email: wwanabdulmuiz@gmail.com
License: UNKNOWN
Platform: UNKNOWN
Classifier: Programming Language :: Python :: 3
Classifier: License :: OSI Approved :: MIT License
Classifier: Operating System :: OS Independent
Requires-Python: >=3.6
Requires-Dist: numpy
Requires-Dist: opencv-python
Requires-Dist: sort
Requires-Dist: ultralytics
